[{"lName":"johnson","inJail":true,"numCrimes":1,"Address":"999 idk lane","Gender":"F","Weight":130,"fName":"margaret","Phone":"123 345 6789","DOB":"2\/3\/1977","Race":"dove tatoo","Height":55,"ID":522,"Age":44,"isAdult":true,"Notes":"dove tatoo"},{"lName":"undermate","inJail":true,"numCrimes":2,"Address":"123 sicamore lane","Gender":"M","Weight":200,"fName":"nate","Phone":"777 444 9999","DOB":"2\/3\/2000","Race":"dove tatoo","Height":65,"ID":797,"Age":21,"isAdult":true,"Notes":"dove tatoo"},{"lName":"karol","inJail":false,"numCrimes":2,"Address":"555 idk lane","Gender":"M","Weight":140,"fName":"harold","Phone":"222 333 4444","DOB":"2\/3\/44","Race":"dove tatoo","Height":65,"ID":777,"Age":54,"isAdult":true,"Notes":"dove tatoo"},{"lName":"bob","inJail":true,"numCrimes":5,"Address":"444 idk lane","Gender":"M","Weight":140,"fName":"tommy","Phone":"555 555 5555","DOB":"2\/3\/44","Race":"dove tatoo","Height":65,"ID":911,"Age":15,"isAdult":true,"Notes":"bad guy"},{"lName":"kidd","inJail":true,"numCrimes":15,"Address":"555 idk lane","Gender":"M","Weight":120,"fName":"billy","Phone":"N\/A","DOB":"5\/4\/33","Race":"white","Height":65,"ID":758,"Age":15,"isAdult":true,"Notes":"dove tatoo"},{"lName":"smith","inJail":false,"numCrimes":5,"Address":"555 idk lane","Gender":"F","Weight":150,"fName":"mary","Phone":"123 345 4567","DOB":"5\/5\/55","Race":"white","Height":65,"ID":319,"Age":55,"isAdult":true,"Notes":"dove tatoo"},{"lName":"doe","inJail":true,"numCrimes":12,"Address":"555 idk lane","Gender":"M","Weight":189,"fName":"john","Phone":"555 444 4444","DOB":"6\/5\/44","Race":"white","Height":56,"ID":796,"Age":89,"isAdult":true,"Notes":"dove tatoo"},{"lName":"mayberry","inJail":true,"numCrimes":15,"Address":"555 idk lane","Gender":"F","Weight":159,"fName":"janet","Phone":"555 444 3333","DOB":"5\/5\/44","Race":"white","Height":65,"ID":89,"Age":55,"isAdult":true,"Notes":"dove tatoo"}]