[
    {
        "lName": "harris",
        "Address": "651 jailbreak road",
        "Gender": "Ff",
        "Weight": "130",
        "fName": "katie",
        "Phone": "555 123 4444",
        "DOB": "april 12 1990",
        "Race": "white",
        "statement": "help ive been robbed",
        "Height": "5\"4",
        "ID": 134,
        "Age": "51",
        "isAdult": true
    },
    {
        "lName": "Clemont",
        "Address": "123 Gervais St., Columbia SC, 29210",
        "Gender": "M",
        "Weight": "N\/A",
        "fName": "Henry",
        "Phone": "803-898-7766",
        "DOB": "N\/A",
        "Race": "N\/A",
        "statement": "the man came in with the gun, and Henry hid behind the cash register.  He saw him leaving in a blue mini-van.",
        "Height": "N\/A",
        "ID": 312,
        "Age": "N\/A",
        "isAdult": true
    },
    {
        "lName": "Clemont",
        "Address": "123 Gervais St., Columbia SC",
        "Gender": "M",
        "Weight": "unknown",
        "fName": "Henry",
        "Phone": "803-898-7766",
        "DOB": "unknown",
        "Race": "unknown",
        "statement": "the man came in with the gun, and Henry hid behind the cash register.  He saw him leaving in a blue mini-van.",
        "Height": "unknown",
        "ID": 215,
        "Age": "unknown",
        "isAdult": true
    }
]